{"idLang":3,"id":"Enlargement","nbLobby":1617,"perNbLobby":0.08472622478386167,"rankNbLobby":5,"cash":6133011.570605188,"rankCash":34,"nbLobbyist":339,"topCountriesNb":[["belgium","414"],["italy","166"],["germany","160"],["france","131"],["united kingdom","107"],["spain","78"],["netherlands","68"],["united states","47"],["austria","45"],["poland","42"]],"topCountriesCash":[["belgium","25988114"],["greece","11404994.5"],["italy","6254970.5"],["france","4622478"],["austria","4094992.5"],["united kingdom","3184985"],["netherlands","2429783"],["germany","2279985"],["sweden","1432497"],["united states","1409994"]],"topLobbyPeople":[["501262611204-82","Austrian Senior Experts Pool","160"],["34440804405-24","UNIVERSIDAD DE ALICANTE","88"],["840436411868-20","Umweltbundesamt Gesellschaft mit beschränkter Haftung","60"],["151486222824-47","Stowarzyszenie Komitet Obrony Demokracji (KOD)","60"],["833094422463-37","INSTITUTO DE PROTEÇÃO AMBIENTAL NACIONAL (IPAN)","50"],["429769926601-54","Asociación Española de Directivos","50"],["205571326534-66","International Music Managers Forum","50"],["236607528721-26","VALORI CRISTIANI","48"],["066400926009-75","INACO-Initiativa pentru Competitivitate","40"],["833652330553-24","The United Nations Organization  for Democracy, Human Rights and Fight Against Corruption","36"]],"topLobbyCash":[["251809024337-33","Αριστοτέλειο Πανεπιστήμιο Θεσσαλονίκης (ΑΠΘ)","10000000"],["272784617259-33","European Institute of Peace","2624500"],["072514125233-04","EUTOP Brussels SPRL","2374999.5"],["10405322962-08","Wirtschaftskammer Österreich","1874999.5"],["110514415986-77","customs4trade","1374999.5"],["84973761187-60","EuroCommerce","1374999.5"],["1083162721-43","Stichting BirdLife Europe","1374999.5"],["19153965510-75","EUROALLIAGES","1124999.5"],["57787966531-03","STARCH EUROPE","1124999.5"],["86853666704-95","Centre for European Policy Studies","1124999.5"]],"lastUpdate":"2020-11-10T09:12:35.543Z"}