{"id":"013755513854-45","name":"Borealis Alliance","registrationDate":"2014-06-25T15:31:09.931+01:00","category":2,"subCategory":4,"legal":"Industry partnership","web":"http://www.borealis.aero","country":"Belgium","headAddress":"Avenue de Cortenbergh, 100","headCity":"Brussels","headPostCode":"1000","headPhone":"(32)27 33 31 33","boss":"Gwen Morgan","bossTitle":"Ms","bossPosition":"Executive Director","membersCount":1,"membersFTE":"1.0","membership":"No","memberOrga":"Avinor, Norway > www.avinor.no&#xd;\nLennuliiklusteeninduse AS (EANS), Estonia > www.eans.ee&#xd;\nFinavia, Finland > www.finavia.fi&#xd;\nIsavia,Iceland > www.isavia.is&#xd;\nIAA, Ireland > www.iaa.ie&#xd;\nLFV, Sweden > www.lfv.se&#xd;\nLatvijas Gaisa Satiksme (LGS), Latvia > www.lgs.lv&#xd;\nNATS, UK > www.nats.aero&#xd;\nNaviair, Denmark > www.naviair.dk","goal":"“To be the leading Air Navigation Service Provider Alliance that enables its Members to drive better performance for stakeholders through business collaboration.”&#xd;<br />&#xd;<br />The Alliance have two objectives:&#xd;<br />&#xd;<br />1.\tPrimary objective: to facilitate cooperation between the Members, on commercially- recognised business partnering principles, that will make a contribution to the operational and financial performance of Members’ air traffic services, including by 2015 making a contribution to the achievement of Single European Sky and ICAO performance targets.&#xd;<br />&#xd;<br />2.\tSecondary objective: to enable Members collectively to be more influential with relevant trade, regulatory and policy bodies in Europe and internationally by developing a common position on major issues and expressing it jointly.","acronym":"","interests":"Transport","euInitiatives":"The Single European Sky initiative and related institutions like SESAR JU and SDM","lastUp":"2018-03-16T12:07:40.072+01:00","customers":"","costAbsolu":"","costRange":"","turnoverAbsolu":0,"turnoverRange":""}