{"id":"018214429231-64","name":"Association of European Journalists","registrationDate":"2017-12-07T18:16:38.139+01:00","category":2,"subCategory":1,"legal":"Association","web":"http://www.aej.org","country":"Belgium","headAddress":"Press Club Europe","headCity":"Bruxelles","headPostCode":"1000","headPhone":"(322)2 01 37 05","boss":"William Horsley","bossTitle":"Mr","bossPosition":"Vice President","membersCount":3,"membersFTE":"0.75","membership":"Observer status at Council of Europe Steering Committee on Media and Information Society, CDMSI, since 2008","memberOrga":"National sections as listed on www.aej.org&#xd;\nPlus AEJ Armenia&#xd;\nAEJ Greece&#xd;\nAEJ Poland","goal":"Promoting free, independent and high quality journalism and media in Europe, safeguarding the welfare of journalists as professionals, engaging with EU institutions and bodies for the above goals, and promoting the AEJ as a network for sharing knowledge, skills and mutual support of members","acronym":"AEJ","interests":"Audiovisual and Media, Enlargement, External Relations, Foreign and Security Policy and Defence, Information Society, Justice and Fundamental Rights","euInitiatives":"Public consultation and formation of High Level Group on fake news and online disinformation;","lastUp":"2017-12-12T18:20:42.177+01:00","customers":"","costAbsolu":"","costRange":"0-9999","turnoverAbsolu":0,"turnoverRange":""}