{"id":"031828616599-65","name":"Redburn (Europe) Limited","registrationDate":"2015-03-16T14:30:18.086+02:00","category":2,"subCategory":3,"legal":"Company limited by shares","web":"http://www.redburn.com","country":"United kingdom","headAddress":"10 Aldermanbury","headCity":"London","headPostCode":"EC2V 7RF","headPhone":"(44)20 70 00 20 20","boss":"Charles Bridge","bossTitle":"Mr","bossPosition":"Director","membersCount":2,"membersFTE":"0.5","membership":"www.londonstockexchange.com","memberOrga":"","goal":"We are an agency stockbroker specialising in European equities.  We buy and sell European equities on behalf of non-retail clients and issue research on such equities.","acronym":"","interests":"Economy, finance and the euro","euInitiatives":"Markets in Financial Instruments Directive II&#xd;<br />Money Laundering Directive IV&#xd;<br />Other policies relevant to the securities industry which could impact our business.","lastUp":"2018-06-05T11:04:01.128+02:00","customers":"","costAbsolu":"","costRange":"","turnoverAbsolu":0,"turnoverRange":""}