{"id":"087139228395-73","name":"Navegação Aérea de Portugal","registrationDate":"2017-09-20T11:01:18.615+02:00","category":2,"subCategory":3,"legal":"Entidade Pública Empresarial","web":"http://www.nav.pt","country":"Portugal","headAddress":"Rua D, Edificio 121, Aeroporto de Lisboa,","headCity":"Lisboa","headPostCode":"1700-008","headPhone":"(351)2 18 55 31 01","boss":"Jorge Ponce de Leão","bossTitle":"","bossPosition":"CEO","membersCount":16,"membersFTE":"6.0","membership":"","memberOrga":"","goal":"A NAV Portugal tem como missão garantir a prestação SEGURA e EFICIENTE de Serviços de Navegação Aérea, contribuindo para a criação de valor e bem-estar da sociedade, desempenhando assim um papel vital no sector da aviação.","acronym":"NAV Portugal E.P.E.","interests":"Business and Industry, Climate Action, Environment, Research and innovation, Trans-European Networks, Transport","euInitiatives":"A NAV Portugal pela atividade que desenvolve tem como principais areas de seguimento as que dizem respeito ao Céu ùnico Europeu - SES -Single European Sky, SESAR, Politicas de transportes, em concreto aviação e aeroportos.","lastUp":"2018-09-24T10:55:44.807+02:00","customers":"","costAbsolu":"","costRange":"100000-199999","turnoverAbsolu":0,"turnoverRange":""}