{"id":"15242613639-84","name":"Verband Deutscher Schleifmittelwerke","registrationDate":"2010-05-21T09:31:24.307+01:00","category":2,"subCategory":4,"legal":"eingetragener Verein","web":"http://www.vds-bonn.de","country":"Germany","headAddress":"Oxfordstrasse, 8","headCity":"Bonn","headPostCode":"53111","headPhone":"(49228)63 55 87","boss":"Klaus Werner","bossTitle":"Mr","bossPosition":"General Secretary","membersCount":1,"membersFTE":"0.25","membership":"Mitglied im europäischen Dachverband FEPA, Kontakte zu Cerame Unie, BusinessEurope, Formacare, EPRA, HSPA, Cefic","memberOrga":"https://www.vds-bonn.de/de/der-vds/mitglieder/","goal":"Ziel des VDS ist die Interessenvertretung der deutschen Schleifmittelindustrie auf nationaler und europäischer Ebene.","acronym":"VDS","interests":"Competition, Consumer Affairs, Customs, Energy, Environment, Public Health, Trade","euInitiatives":"Product Safety Directive, classification of substances (CLP), Registration and Authorisation (REACH), CMD, BREF STS, BREF CER","lastUp":"2018-01-16T20:52:51.561+01:00","customers":"","costAbsolu":"","costRange":"25000-49999","turnoverAbsolu":0,"turnoverRange":""}