{"id":"233075634836-35","name":"EU-Australia Round Table","registrationDate":"2019-05-17T10:01:43.182+02:00","category":2,"subCategory":4,"legal":"Not for profit - No legal status","web":"","country":"Belgium","headAddress":"Hume Brophy","headCity":"Brussels","headPostCode":"1040","headPhone":"(32)22 34 68 60","boss":"Jill Craig","bossTitle":"Ms","bossPosition":"Managing Director","membersCount":1,"membersFTE":"0.25","membership":"None","memberOrga":"","goal":"The EU-Australia Round Table (EART) is a cross-sector alliance of EU and Australian business leaders who support the successful conclusion of an EU-Australia Free Trade Agreement (FTA).","acronym":"EART","interests":"Agriculture and Rural Development, Banking and financial services, Borders and Security, Budget, Business and Industry, Climate Action, Communication, Competition, Consumers, Culture, Culture and media, Customs, Digital economy and society, Economy, finance and the euro, Education and training, Employment and Social Affairs, Energy, Enlargement, Environment, European Neighbourhood Policy, External Relations, Food Safety, Foreign affairs and security policy, Fraud prevention, Humanitarian aid and civil protection, Institutional affairs, International co-operation and development, Justice and Fundamental Rights, Maritime affairs and fisheries, Migration and asylum, Public Health, Regional Policy, Research and innovation, Single market, Sport, Taxation, Trade, Trans-European Networks, Transport, Youth","euInitiatives":"The EART will act as a platform for issues of common interest in the FTA negotiations between the EU and Australia.","lastUp":"2019-05-17T10:02:16.634+02:00","customers":"","costAbsolu":0,"costRange":"","turnoverAbsolu":0,"turnoverRange":""}