{"id":"370355823557-30","name":"FRAMETEC GROUP LIMITED","registrationDate":"2016-09-24T15:13:43.476+02:00","category":2,"subCategory":3,"legal":"LTD","web":"","country":"United kingdom","headAddress":"6A DICKENSON'S PLACE","headCity":"LONDON","headPostCode":"SE 25 5 HL","headPhone":"(44)74 18 47 40 40","boss":"ARISTIDIS GLINIS","bossTitle":"Mr","bossPosition":"CEO","membersCount":3,"membersFTE":"0.75","membership":"","memberOrga":"","goal":"\"Frametec Group Limited\" is a company promoting, marketing, distributing and selling technologically advanced equipment used for security and statistic purposes.","acronym":"","interests":"Borders and Security, Education and training, Foreign affairs and security policy, International co-operation and development, Justice and Fundamental Rights, Research and innovation, Single market, Trade, Transport","euInitiatives":"International trade, \"ETIAS\" program, \"EPRIS\" program, Home affairs, Interoperability of information systems for migration and security, AMIF / ISF","lastUp":"2019-08-04T14:02:08.064+02:00","customers":"","costAbsolu":"","costRange":"100000-199999","turnoverAbsolu":0,"turnoverRange":""}