{"id":"457753034857-23","name":"Alliance Professionnelle des Agents Commerciaux","registrationDate":"2019-05-16T18:53:45.565+02:00","category":2,"subCategory":4,"legal":"Association","web":"https://www.apacfrance.com/","country":"France","headAddress":"71 Rue Pierre Corneille","headCity":"LYON","headPostCode":"69006","headPhone":"(33)4 78 52 61 75","boss":"Olivier MAZOYER","bossTitle":"Mr","bossPosition":"President","membersCount":2,"membersFTE":"0.5","membership":"https://iucab.com/","memberOrga":"","goal":"Our Professional Organization represents and defends the interests of the French Commercial Agency in our Territory, but also internationally, which brings together more than 600.000 companies in the World.&#xd;<br />These Commercial Agencies are SME specialized in Commercial Marketing. Present in all sectors of the economy, they contribute to the growth of Manufacturers who wish to develop their sales.&#xd;<br />Our profession represents 25.000 companies, more than 52.000 professionals and&#xd;<br />3 billion 500 million euros in turnover.&#xd;<br />Our members work as well in the marketing of everyday products as high technology products. 40% of the agents represent at least 1 EU-foreign principal.&#xd;<br />Commercial Agencies.&#xd;<br />APAC is member of Internationnaly United Commercial Agents and Brokers (IUCAB).","acronym":"APAC","interests":"Borders and Security, Business and Industry, Competition, Consumers, Customs, Digital economy and society, Economy, finance and the euro, Education and training, Institutional affairs, International co-operation and development, Trade, Trans-European Networks","euInitiatives":"All files about trade, commercial agency, distribution, competition, vertical agreement.","lastUp":"2019-05-16T18:54:45.540+02:00","customers":"","costAbsolu":"","costRange":"0-9999","turnoverAbsolu":0,"turnoverRange":""}