{"id":"510331919557-74","name":"Constantin Film AG","registrationDate":"2015-11-16T17:04:34.788+02:00","category":2,"subCategory":3,"legal":"AG","web":"https://www.constantin-film.de/","country":"Germany","headAddress":"Feilitzschstrasse 6","headCity":"München","headPostCode":"80802","headPhone":"(49)8 94 44 46 00","boss":"Gero Worstbrock","bossTitle":"Mr","bossPosition":"Prokurist","membersCount":1,"membersFTE":"0.25","membership":"Bundesverband Audiovisuelle Medien e.V.&#xd;\nVerband der Filmverleiher e.V.&#xd;\nAllianz Deutscher Produzenten – Film &amp; Fernsehen e.V.&#xd;\nund weitere","memberOrga":"","goal":"Produktion, Verleih, Vertrieb und Lizenzhändler von audiovisuellen Inhalten","acronym":"","interests":"Culture, Culture and media","euInitiatives":"Digital Single Market","lastUp":"2018-09-27T13:02:41.563+02:00","customers":"","costAbsolu":"","costRange":"0-9999","turnoverAbsolu":0,"turnoverRange":""}