{"id":"518900326020-12","name":"Občianske združenie Kolysočka - Kolíska","registrationDate":"2017-02-21T15:05:56.572+01:00","category":3,"subCategory":2,"legal":"občianske združenie","web":"http://www.rusinskyjazyk.sk","country":"Slovakia","headAddress":"Solivarská 70","headCity":"Prešov","headPostCode":"080 05","headPhone":"(421)9 05 86 33 69","boss":"Ľuba Kráľová","bossTitle":"Ms","bossPosition":"štatutárka a predsedníčka","membersCount":2,"membersFTE":"0.5","membership":"","memberOrga":"OZ Kolysočka - Kolíska je jedna organizácia, netvoria ju iné organizácie.","goal":"OZ Kolysočka - Kolíska sa orientuje na deti Rusínov a snaží sa obrodiť tradície a jazyk vymierajúcej národnostnej menšiny Rusínov na území Slovenska.","acronym":"OZ Kolysočka - Kolís","interests":"Audiovisual and Media, Communication, Culture, Development, Education, Employment and Social Affairs, Youth","euInitiatives":"- národnostná politika&#xd;<br />- vzdelávacia politika&#xd;<br />. kultúrna politika","lastUp":"2017-02-21T15:09:11.764+01:00","customers":"","costAbsolu":"","costRange":"","turnoverAbsolu":0,"turnoverRange":""}