{"id":"575921329575-71","name":"Ariane Koek","registrationDate":"2018-01-13T18:12:03.815+01:00","category":1,"subCategory":8,"legal":"none","web":"","country":"United kingdom","headAddress":"17 Shandon Road","headCity":"London","headPostCode":"SW4 9HS","headPhone":"(44)77 89 68 09 97","boss":"Ariane Koek","bossTitle":"Ms","bossPosition":"Independent Consultant","membersCount":1,"membersFTE":"1.0","membership":"Salzburg Global Forum (Austria)&#xd;\n&#xd;\nClore Fellowship (UK)&#xd;\n&#xd;\nForum D'Avignon (France)","memberOrga":"None.","goal":"My consultancy works with individuals, scientific and cultural organisations and foundations in helping them imagine and create new strategy and directions.&#xd;<br />&#xd;<br />The focus is mainly but not exclusively on the arts/science field.&#xd;<br />&#xd;<br />I am also a writer and independent curator.&#xd;<br />I work mainly in Switzerland, Sweden and Italy.&#xd;<br />&#xd;<br />Current clients include Science Gallery Venice  at Ca Foscari University, Italy which is part of the Science Gallery International network colliding arts and science, the city of Kyoto in Japan, Bildmuseet in Sweden which is also part of Umea University.&#xd;<br />&#xd;<br />I am also a cultural advisor and I am on the cultural board for the JRC - Ispra, Italy, HEL (House of Electronic Arts Basel) and CERN.","acronym":"","interests":"Communication, Culture, Research and Technology, Trans-European Networks","euInitiatives":"There are no EU initiatives, policies and legislative files targeted by my consultancy currently.","lastUp":"2018-01-16T12:09:03.274+01:00","customers":"","costAbsolu":"","costRange":"10000-24999","turnoverAbsolu":"","turnoverRange":"0-99999"}