{"id":"640518629632-60","name":"Unione Forestali Carabinieri e Diritti","registrationDate":"2018-01-17T09:31:42.984+02:00","category":3,"subCategory":2,"legal":"Associazione Culturale","web":"http://www.unforced.it","country":"Italy","headAddress":"Via Torino n. 95","headCity":"Roma","headPostCode":"00184","headPhone":"(39)33 86 11 90 01","boss":"Danilo Scipio","bossTitle":"Mr","bossPosition":"Presidente","membersCount":2,"membersFTE":"1.5","membership":"","memberOrga":"","goal":"L’Associazione persegue i seguenti fini:&#xd;<br />&#xd;<br />fornire il proprio contributo, progettuale e tecnico-professionale, nell’elaborazione di riforme legislative attinenti il sistema della sicurezza, con particolare riguardo ai temi ambientali ed agroalimentari, in conformità ai principi della Costituzione e dei trattati dell’Unione Europea;&#xd;<br />promuovere iniziative, eventi e dibattiti, attività culturali, sociali e informative al fine di contribuire al miglioramento dei regimi di sicurezza, legalità e giustizia, anche nella prospettiva di riforme legislative e organizzative;&#xd;<br />adoperarsi per il pieno ed effettivo riconoscimento al personale dell'Arma dei Carabinieri e delle altre istituzioni a struttura militare dei diritti sindacali, di associazione, di libera manifestazione del pensiero e di associazione professionale in coerenza con il disposto degli articoli: 52 della Costituzione italiana, 12 della Carta dei diritti fondamentali dell’Unione Europea e 11 della Convenzione europea dei diritti dell’Uomo e in linea con quanto avviene negli altri Stati europei a democrazia avanzata;&#xd;<br />contribuire a diffondere tra i cittadini, anche all'interno degli istituti scolastici di formazione, il rispetto della legalità ed una maggiore cultura ambientale, nella consapevolezza che solo attraverso il rispetto della natura, in ogni sua forma, è possibile preservare l'immenso patrimonio naturalistico dell’Italia;&#xd;<br />sviluppare costruttivi e trasparenti rapporti con i cittadini;&#xd;<br />contribuire ad iniziative di studio e di progetto per il rispetto della legalità ed il contrasto ai reati contro l'ambiente;&#xd;<br />organizzare e partecipare a manifestazioni pubbliche per il perseguimento delle finalità istituzionali;","acronym":"UNFORCED","interests":"Agriculture and Rural Development, Energy, Environment, Food Safety","euInitiatives":"L'Associazione intende porre in essere le seguenti attività:&#xd;<br />Attività di sensibilizzazione, progettuale, di analisi nei temi della politica e della sicurezza ambientale, forestale, agroalimentare;&#xd;<br />Monitoraggio dell’attività legislativa e attività di proposte, richieste e suggerimenti intesa a perseguire interessi di salvaguardia, protezione e miglioramento della tutela dell’ambiente, del paesaggio e dell’ecosistema;&#xd;<br />Possibilità di partecipare ad audizioni, consultazioni anche on line, o inviare documenti alle Commissioni del Parlamento Europeo nelle materie di interesse.","lastUp":"2019-07-16T08:31:43.180+02:00","customers":"","costAbsolu":0,"costRange":"","turnoverAbsolu":0,"turnoverRange":""}