{"id":"71462686997-10","name":"Independent Diplomat","registrationDate":"2011-10-21T21:02:19.978+02:00","category":3,"subCategory":2,"legal":"501(c)3 non-profit organisation","web":"http://www.independentdiplomat.org","country":"United states","headAddress":"246 5th Avenue","headCity":"New York","headPostCode":"10001","headPhone":"(1)60 93 06 52 44","boss":"Carne Ross","bossTitle":"Mr","bossPosition":"Executive Director","membersCount":2,"membersFTE":"2.0","membership":"","memberOrga":"","goal":"Independent Diplomat (ID) is a unique, non-profit advisory group in the world of diplomacy.&#xd;<br />&#xd;<br />ID provides confidential advice and practical assistance in diplomatic strategy and technique to governments, political groups, international organisations and NGOs.  We work to amplify the voices of those who have most at stake in diplomatic processes.  Our work thus promotes greater inclusiveness in diplomacy, and contributes to more just and sustainable solutions to international problems and conflict.","acronym":"ID","interests":"Climate Action, External Relations, Foreign affairs and security policy, Humanitarian aid and civil protection, Institutional affairs, International co-operation and development, Justice and Fundamental Rights, Maritime affairs and fisheries, Regional Policy","euInitiatives":"CSDP, trade, development, accession, regional policies, climate change, peace and security.","lastUp":"2019-10-15T17:34:33.132+02:00","customers":"","costAbsolu":"","costRange":"200000-299999","turnoverAbsolu":0,"turnoverRange":""}