{"id":"780774426283-81","name":"Fels-Werke","registrationDate":"2017-03-28T14:36:38.060+01:00","category":2,"subCategory":3,"legal":"GmbH","web":"http://www.fels.de","country":"Germany","headAddress":"Geheimrat-Ebert-Straße 12","headCity":"Goslar","headPostCode":"38640","headPhone":"(49)0 53 21 70 30","boss":"Burkhard Naffin","bossTitle":"Mr","bossPosition":"CEO","membersCount":1,"membersFTE":"0.25","membership":"BVK; EULA; ILA; BBS; Bundesverband Porenbetonindustrie; Bundesverband Kalksandsteinindustrie e.V.; Deutsche Vereinigung für Wasserwirtschaft, Abwasser; Düngekalk Hauptgemeinschaft; VDI; Industrieverband WerkMörtel e.V. (IWM); FGSV - Forschungsgesellschaft für Strassen- u. Verkehrswesen; BVSE; Gipsverband","memberOrga":"","goal":"Gewinnung und Veredelung von Kalk- und Kalksteinprodukten.&#xd;<br />Versorgung von Schlüsselindustrien mit diesen spezifischen Rohstoffen in deren Wertschöpfungsprozess (Stahl-, Chemische-, Baustoffindustrie sowie Umweltanwendungen wie Luftreinhaltung, Trink-, Abwasseraufbereitung, Landwirtschaft u.a.)","acronym":"","interests":"Climate Action, Energy, Environment, Research and innovation","euInitiatives":"Emission Trading System (ETS), REACH, Baunormen, Umweltnormen, Biozid Verordnung,   IED Richtlinie","lastUp":"2019-02-17T20:22:57.104+01:00","customers":"","costAbsolu":"","costRange":"0-9999","turnoverAbsolu":0,"turnoverRange":""}