{"id":"856967934319-47","name":"Autonomous Mobility A/S","registrationDate":"2019-03-20T14:55:58.016+01:00","category":2,"subCategory":3,"legal":"plc","web":"http://www.amobility.dk","country":"Denmark","headAddress":"Autonomous Mobility A/S","headCity":"Kgs Lyngby","headPostCode":"2800","headPhone":"(45)25 46 06 33","boss":"Peter Sorgenfrei","bossTitle":"Mr","bossPosition":"CEO","membersCount":29,"membersFTE":"29.0","membership":"","memberOrga":"","goal":"To expedite the transition to shared, sustainable and autonomous transportation of people and goods.","acronym":"","interests":"Transport","euInitiatives":"Public transportation, self-driving technologies, cargo and passenger drones, parcel drones and legislation on autonomous cars.","lastUp":"2019-03-20T14:56:20.362+01:00","customers":"","costAbsolu":"","costRange":"","turnoverAbsolu":0,"turnoverRange":""}