{"id":"881177926694-39","name":"Driver assistance systems and self-driving car","registrationDate":"2017-04-09T23:32:17.028+01:00","category":6,"subCategory":9,"legal":"Keine","web":"https://www.linkedin.com/groups/5065744","country":"Germany","headAddress":"Surauer Straße 26","headCity":"Berlin","headPostCode":"","headPhone":"(49)1 51 71 32 11 84","boss":"Christian Fraunholz","bossTitle":"Mr","bossPosition":"Eigentümer","membersCount":10,"membersFTE":"2.5","membership":"","memberOrga":"https://www.linkedin.com/groups/5065744","goal":"Die Aufgabe der LinkedIn Gruppe ist das Vernetzen und Informieren von Experten im Bereich Fahrerassistenzsysteme und selbstfahrende Autos","acronym":"DASSC","interests":"Communication, Environment, Financial Stability, Financial Services and Capital Markets Union , Research and Technology, Transport","euInitiatives":"Forschungs- und Innovationsprogramme (H2020) und Konsultation zur Schaffung der europäischen Datenwirtschaft","lastUp":"2017-04-09T23:38:24.357+01:00","customers":"","costAbsolu":0,"costRange":"","turnoverAbsolu":0,"turnoverRange":""}