{"id":"912426012052-70","name":"WBO Verband Baden-Württembergischer Omnibusunternehmer e. V.","registrationDate":"2013-10-09T11:05:36.888+01:00","category":2,"subCategory":4,"legal":"Eingetragener Verein","web":"http://www.busforum.de","country":"Germany","headAddress":"Dornierstraße 3","headCity":"Böblingen","headPostCode":"71034","headPhone":"(07031)62 31 01","boss":"Witgar Dr. Weber","bossTitle":"Mr","bossPosition":"Geschäftsführer","membersCount":1,"membersFTE":"0.25","membership":"bdo - Bundesverband mit Sitz in Berlin","memberOrga":"","goal":"Der Verband WBO ist Zusammenschluss privater Omnibusunternehmen. Er vertritt allgemeine und überbetriebliche, insbesondere die gewerbepolitischen Interessen des privaten Omnibusgewerbes. Der Verband fördert die Fortentwicklung des ÖPNV wie auch des Freizeit- und touristischen Verkehrs mit Omnibussen, mit den Zielen der Kundenorientierung, der Wirtschaftlichkeit und der Nachhaltigkeit. Er tritt für die Förderung der Unternehmen, die diese Ziele verfolgen ein, dess sie leisten eine wesentlichen Beitrag für eine umweltschonende Mobilität. Der Verband richtet sein Handeln an den am Markt tätigen Verkehrsunternehmen aus, deren Aufgabe es ist, Personenverkehr zu planen, organisieren und durchzuführen.","acronym":"WBO e. V.","interests":"Climate Action, Competition, Employment and Social Affairs, Environment, Taxation, Transport","euInitiatives":"Er vertritt allgemeine und überbetriebliche, insbesondere die gewerbepolitischen Interessen des privaten Omnibusgewerbes. Der Verband fördert die Fortentwicklung des ÖPNV wie auch des Freizeit- und touristischen Verkehrs mit Omnibussen, mit den Zielen der Kundenorientierung, der Wirtschaftlichkeit und der Nachhaltigkeit.","lastUp":"2018-02-16T12:03:26.922+01:00","customers":"","costAbsolu":"","costRange":"0-9999","turnoverAbsolu":0,"turnoverRange":""}