{"id":"988976411591-02","name":"UNETO-VNI","registrationDate":"2013-07-16T10:04:05.454+01:00","category":2,"subCategory":4,"legal":"association","web":"http://www.uneto-vni.nl","country":"Netherlands","headAddress":"Bredewater, 20","headCity":"Zoetermeer","headPostCode":"2700 AD","headPhone":"(079)3 25 06 50","boss":"Erik van Engelen","bossTitle":"Mr","bossPosition":"Director","membersCount":65,"membersFTE":"57.5","membership":"","memberOrga":"","goal":"Employers interests in the installation sector","acronym":"UNETO-VNI","interests":"Climate Action, Economic and Financial Affairs, Employment and Social Affairs, Energy, Enterprise, Information Society, Research and Technology","euInitiatives":"Energy","lastUp":"2017-03-23T23:00:30.801+01:00","customers":"","costAbsolu":"","costRange":"0-9999","turnoverAbsolu":0,"turnoverRange":""}